venpy/__about__.py
venpy/__init__.py
venpy/aslist.py
venpy/aslist.pyi
venpy/cache.py
venpy/cache.pyi
venpy/context.py
venpy/index_by.py
venpy/keydefaultdict.py
venpy/none_throws.py
venpy/py.typed
venpy-0.2.3.dist-info/METADATA
venpy-0.2.3.dist-info/WHEEL
venpy-0.2.3.dist-info/RECORD
